opendata_research_tools/__init__.py
opendata_research_tools/version.py
opendata_research_tools/search/__init__.py
opendata_research_tools/search/base.py
opendata_research_tools/search/chembl.py
opendata_research_tools/search/clinical_trials.py
opendata_research_tools/search/ncbi_gene.py
opendata_research_tools/search/news.py
opendata_research_tools/search/patent.py
opendata_research_tools/search/protein_structure.py
opendata_research_tools/search/pubchem.py
opendata_research_tools/search/pubmed.py
opendata_research_tools/search/uniprot.py
opendata_research_tools/search/wikidata.py
opendata_research_tools/utils/__init__.py
opendata_research_tools/utils/gene_resolver.py
opendata_research_tools/utils/http_cache.py
opendata_research_tools-0.1.1.dist-info/METADATA
opendata_research_tools-0.1.1.dist-info/WHEEL
opendata_research_tools-0.1.1.dist-info/licenses/LICENSE
opendata_research_tools-0.1.1.dist-info/RECORD
