Metadata-Version: 2.4
Name: opendata-research-tools
Version: 0.1.1
Summary: Lightweight Python library for searching biomedical databases (PubMed, NCBI Gene, UniProt, ChEMBL, etc.)
Project-URL: Homepage, https://github.com/xxxxx/opendata-research-tools
Project-URL: Documentation, https://opendata-research-tools.readthedocs.io
Project-URL: Repository, https://github.com/xxxxx/opendata-research-tools
Project-URL: Issues, https://github.com/xxxxx/opendata-research-tools/issues
Project-URL: Changelog, https://github.com/xxxxx/opendata-research-tools/blob/main/CHANGELOG.md
Author-email: "greet-essence-6s@icloud.com" <greet-essence-6s@icloud.com>
License: MIT
License-File: LICENSE
Keywords: bioinformatics,biomedical-databases,chembl,data-search,ncbi,open-data,pubmed,research-tools,scientific-literature,uniprot
Classifier: Development Status :: 3 - Alpha
Classifier: Intended Audience :: Developers
Classifier: Intended Audience :: Science/Research
Classifier: License :: OSI Approved :: MIT License
Classifier: Programming Language :: Python :: 3
Classifier: Programming Language :: Python :: 3.10
Classifier: Programming Language :: Python :: 3.11
Classifier: Programming Language :: Python :: 3.12
Classifier: Programming Language :: Python :: 3.13
Classifier: Topic :: Scientific/Engineering :: Bio-Informatics
Classifier: Topic :: Scientific/Engineering :: Information Analysis
Requires-Python: >=3.10
Requires-Dist: requests>=2.31.0
Requires-Dist: twine>=6.2.0
Provides-Extra: all
Requires-Dist: black>=23.0.0; extra == 'all'
Requires-Dist: mkdocs-material>=9.0.0; extra == 'all'
Requires-Dist: mkdocs>=1.5.0; extra == 'all'
Requires-Dist: mkdocstrings[python]>=0.24.0; extra == 'all'
Requires-Dist: mypy>=1.0.0; extra == 'all'
Requires-Dist: pytest-cov>=4.0.0; extra == 'all'
Requires-Dist: pytest-mock>=3.12.0; extra == 'all'
Requires-Dist: pytest>=7.0.0; extra == 'all'
Requires-Dist: python-dotenv>=1.0.0; extra == 'all'
Requires-Dist: ruff>=0.1.0; extra == 'all'
Requires-Dist: types-requests>=2.31.0; extra == 'all'
Provides-Extra: dev
Requires-Dist: black>=23.0.0; extra == 'dev'
Requires-Dist: mypy>=1.0.0; extra == 'dev'
Requires-Dist: pytest-cov>=4.0.0; extra == 'dev'
Requires-Dist: pytest-mock>=3.12.0; extra == 'dev'
Requires-Dist: pytest>=7.0.0; extra == 'dev'
Requires-Dist: python-dotenv>=1.0.0; extra == 'dev'
Requires-Dist: ruff>=0.1.0; extra == 'dev'
Requires-Dist: types-requests>=2.31.0; extra == 'dev'
Provides-Extra: docs
Requires-Dist: mkdocs-material>=9.0.0; extra == 'docs'
Requires-Dist: mkdocs>=1.5.0; extra == 'docs'
Requires-Dist: mkdocstrings[python]>=0.24.0; extra == 'docs'
